{"round": {"round_id": "2026-07-22_08", "date": "2026-07-22", "slot": "08:00", "next_slot": "12:00", "captured_at": "1784689393", "server_time": "1784691719", "items": [{"name": "\u666e\u901a\u8840\u8109\u79d8\u836f", "category": "\u8840\u8109\u4fee\u6539\u9053\u5177", "price": 160000, "currency": "bei", "purchase_limit": "3", "description": "\u80fd\u5524\u9192\u8840\u8109\u529b\u91cf\u7684\u8fdc\u53e4\u79d8\u836f\uff0c\u4f7f\u7cbe\u7075\u83b7\u5f97\u666e\u901a\u7cfb\u8840\u8109\u3002", "icon_url": "https://ug.tapimg.com/roco-merchant/sku/pu_tong_xue_mai_mi_yao_96da9a1d.png", "confidence": 0.99}, {"name": "\u5e7b\u7cfb\u7c89\u5c18", "category": "\u70bc\u91d1\u6750\u6599", "price": 500, "currency": "bei", "purchase_limit": "100", "description": "\u5e38\u89c1\u7684\u70bc\u91d1\u6750\u6599\uff0c\u8574\u542b\u5c11\u91cf\u5e7b\u7cfb\u9b54\u6cd5\uff0c\u662f\u5408\u6210\u6280\u80fd\u77f3\u7684\u4e3b\u8981\u89e6\u5a92\u3002", "icon_url": "https://ug.tapimg.com/roco-merchant/sku/huan_xi_fen_chen_09756633.png", "confidence": 0.99}]}}